{"0": "ask_ABC", "1": "ask_ADC", "2": "ask_AIC", "3": "ask_AIVC", "4": "ask_AMC", "5": "ask_APD", "6": "ask_APDLifeSkillsClub", "7": "ask_APD_BSC", "8": "ask_APD_toc", "9": "ask_AVSC", "10": "ask_Aptis_ESOL", "11": "ask_CMA", "12": "ask_Cambridge", "13": "ask_IELTS", "14": "ask_SMC", "15": "ask_TOEFL_ITP", "16": "ask_TOEFL_iBT", "17": "ask_TOEIC", "18": "ask_Vstep", "19": "ask_YAA", "20": "ask_YJAC", "21": "ask_ability", "22": "ask_admissions_link", "23": "ask_admissions_online", "24": "ask_bus_19", "25": "ask_cai_thien", "26": "ask_cc_dau_ra", "27": "ask_chuong_trinh_hoc_dll", "28": "ask_chuong_trinh_hoc_ktkds", "29": "ask_chuong_trinh_hop_tac", "30": "ask_clb", "31": "ask_clb_TA", "32": "ask_clb_bong_da", "33": "ask_clb_br", "34": "ask_clb_nckh", "35": "ask_clb_nha_dau_tu_tre", "36": "ask_clb_tt", "37": "ask_cocau_tcochuc", "38": "ask_ct_tinh_thang4", "39": "ask_dang_ky_tin_chi", "40": "ask_dao_tao_ts", "41": "ask_de_xe", "42": "ask_dll", "43": "ask_have_hold_an_exam", "44": "ask_hinh_thuc_dky_xt", "45": "ask_ho_so_xt", "46": "ask_hoc_lai", "47": "ask_hotline_kts", "48": "ask_hp_kts", "49": "ask_h\u0111_nk", "50": "ask_ic3", "51": "ask_ict", "52": "ask_kts", "53": "ask_main_link", "54": "ask_mos", "55": "ask_muc_khen_thuong_hoc_bongdt", "56": "ask_nghanh_clc", "57": "ask_nghanh_dt", "58": "ask_ptts_kts", "59": "ask_ptts_kts_cc", "60": "ask_ptts_kts_hoc_ba", "61": "ask_ptts_kts_hsg", "62": "ask_ptts_kts_tuyen_danh_gia_nang_luc", "63": "ask_ptts_kts_tuyen_thang", "64": "ask_qly_dtu", "65": "ask_qt_mien_hoc_tin_hoc", "66": "ask_quoc_phong", "67": "ask_quy_doi_ta", "68": "ask_tc_kts", "69": "ask_tg_ho_so", "70": "ask_tham_quan_dn", "71": "ask_thi_dau_vao", "72": "ask_thoi_gian_hoc_trong_ngay", "73": "ask_thu_vien", "74": "ask_to_hop_xt", "75": "ask_van_phong_kts", "76": "cach_xet_tuyen", "77": "cao_dang", "78": "che", "79": "ch\u00e0o", "80": "co_so_vat_chat", "81": "dung_tai_lieu_thi", "82": "khen", "83": "kytucxa", "84": "ma_tuyen_sinh", "85": "quy_doi_AptisESOL", "86": "quy_doi_Cambridge", "87": "quy_doi_IELTS", "88": "quy_doi_TOEFL_ITP", "89": "quy_doi_TOEFL_iBT", "90": "quy_doi_TOEIC", "91": "quy_doi_Vstep", "92": "quy_doi_ic3", "93": "quy_doi_mos", "94": "quy_doi_thang4", "95": "so_luong_chi_tieu", "96": "thankyou", "97": "t\u1ea1m bi\u1ec7t", "98": "xep_lich_hoc"}